topsis/__init__.py
topsis/topsis.py
topsis_saanvi_102483080-2.0.0.dist-info/METADATA
topsis_saanvi_102483080-2.0.0.dist-info/WHEEL
topsis_saanvi_102483080-2.0.0.dist-info/entry_points.txt
topsis_saanvi_102483080-2.0.0.dist-info/top_level.txt
topsis_saanvi_102483080-2.0.0.dist-info/RECORD
