Metadata-Version: 2.4
Name: topsis-saanvi-102483080
Version: 2.0.0
Summary: TOPSIS implementation for multi-criteria decision making
Author: Saanvi Wadhwa
Author-email: your_email@gmail.com
Requires-Dist: pandas
Requires-Dist: numpy
Dynamic: author
Dynamic: author-email
Dynamic: description
Dynamic: description-content-type
Dynamic: requires-dist
Dynamic: summary
